hedgehog/__init__.py
hedgehog/server/__init__.py
hedgehog/server/_version.py
hedgehog/server/hedgehog_server.py
hedgehog/server/server.py
hedgehog/server/simulator.py
hedgehog/server/subscription.py
hedgehog/server/handlers/__init__.py
hedgehog/server/handlers/hardware.py
hedgehog/server/handlers/process.py
hedgehog/server/hardware/__init__.py
hedgehog/server/hardware/mocked.py
hedgehog/server/hardware/simulated.py
hedgehog/server/hardware/serial/__init__.py
hedgehog/server/hardware/serial/constants.py
hedgehog_server-0.9.1.dist-info/LICENSE
hedgehog_server-0.9.1.dist-info/METADATA
hedgehog_server-0.9.1.dist-info/WHEEL
hedgehog_server-0.9.1.dist-info/entry_points.txt
hedgehog_server-0.9.1.dist-info/top_level.txt
hedgehog_server-0.9.1.dist-info/RECORD
